ephemerista/__init__.py
ephemerista/angles.py
ephemerista/assets.py
ephemerista/bodies.py
ephemerista/frames.py
ephemerista/math.py
ephemerista/py.typed
ephemerista/scenarios.py
ephemerista/time.py
ephemerista/uuid_utils.py
ephemerista/analysis/__init__.py
ephemerista/analysis/coverage.py
ephemerista/analysis/link_budget.py
ephemerista/analysis/navigation.py
ephemerista/analysis/visibility.py
ephemerista/analysis/resources/__init__.py
ephemerista/analysis/resources/ne_110m_land.README.html
ephemerista/analysis/resources/ne_110m_land.VERSION.txt
ephemerista/analysis/resources/ne_110m_land.cpg
ephemerista/analysis/resources/ne_110m_land.dbf
ephemerista/analysis/resources/ne_110m_land.prj
ephemerista/analysis/resources/ne_110m_land.shp
ephemerista/analysis/resources/ne_110m_land.shx
ephemerista/comms/__init__.py
ephemerista/comms/antennas.py
ephemerista/comms/channels.py
ephemerista/comms/frequencies.py
ephemerista/comms/receiver.py
ephemerista/comms/systems.py
ephemerista/comms/transmitter.py
ephemerista/comms/utils.py
ephemerista/constellation/__init__.py
ephemerista/constellation/design.py
ephemerista/constellation/plane.py
ephemerista/coords/__init__.py
ephemerista/coords/anomalies.py
ephemerista/coords/events.py
ephemerista/coords/shapes.py
ephemerista/coords/trajectories.py
ephemerista/coords/twobody.py
ephemerista/jars/ephemeristaJava-0.0.1-SNAPSHOT.jar
ephemerista/plot/__init__.py
ephemerista/plot/groundtrack.py
ephemerista/plot/utils.py
ephemerista/propagators/__init__.py
ephemerista/propagators/events.py
ephemerista/propagators/oem.py
ephemerista/propagators/sgp4.py
ephemerista/propagators/orekit/__init__.py
ephemerista/propagators/orekit/ccsds.py
ephemerista/propagators/orekit/conversions.py
ephemerista/propagators/orekit/numerical.py
ephemerista/propagators/orekit/semianalytical.py
ephemerista-0.1.0a16.dist-info/METADATA
ephemerista-0.1.0a16.dist-info/WHEEL
ephemerista-0.1.0a16.dist-info/licenses/LICENSE.txt
ephemerista-0.1.0a16.dist-info/RECORD
