Metadata-Version: 2.4
Name: ephemerista
Version: 0.1.0a16
Summary: Space mission analysis for telecommunications and satellite constellations
Project-URL: Documentation, https://docs.ephemerista.space
Project-URL: Issues, https://gitlab.com/librespacefoundation/ephemerista/ephemerista-simulator/-/issues
Project-URL: Source, https://gitlab.com/librespacefoundation/ephemerista/ephemerista-simulator
Author-email: Helge Eichhorn <helge@libre.space>, Clément Jonglez <clement@jonglez.space>, Andrei Zisu <matzipan@gmail.com>, Calum Hervieu <calumjhervieu@gmail.com>, Victoria Malyshkina <victoria@libre.space>
License: AGPL-3.0-or-later
License-File: LICENSE.txt
Classifier: Development Status :: 3 - Alpha
Classifier: Programming Language :: Python
Classifier: Programming Language :: Python :: 3.12
Classifier: Programming Language :: Python :: Implementation :: CPython
Classifier: Programming Language :: Python :: Implementation :: PyPy
Requires-Python: <3.14,>=3.12
Requires-Dist: antimeridian~=0.4
Requires-Dist: folium~=0.20
Requires-Dist: geojson-pydantic~=2.0
Requires-Dist: geojsoncontour~=0.5
Requires-Dist: geopandas~=1.1
Requires-Dist: h3~=4.3
Requires-Dist: itur~=0.4
Requires-Dist: jdk4py~=21.0
Requires-Dist: lox-space==0.1.0a27
Requires-Dist: matplotlib~=3.10
Requires-Dist: numpy>=1.16.0
Requires-Dist: orekit-jpype~=13.1
Requires-Dist: pandas~=2.3
Requires-Dist: plotly~=6.3
Requires-Dist: pydantic-numpy~=8.0
Requires-Dist: pydantic~=2.11
Requires-Dist: scipy~=1.16
